AUTHORS
LICENSE
MANIFEST.in
README.rst
setup.py
ixml/__init__.py
ixml/api.py
ixml.egg-info/PKG-INFO
ixml.egg-info/SOURCES.txt
ixml.egg-info/dependency_links.txt
ixml.egg-info/top_level.txt
ixml/backends/__init__.py
ixml/backends/lxmliterparse.py
ixml/builders/__init__.py
ixml/builders/dictbuilder.py
ixml/builders/interface.py