Metadata-Version: 1.1
Name: ixml
Version: 0.1.0
Summary: iXML is an iterative event-driven XML parser with a standard Python iterator interface.
Home-page: https://bitbucket.org/YAmikep/ixml
Author: Michael Palumbo
Author-email: michael.palumbo87@gmail.com
License: Copyright (C) 2013, Michael Palumbo
